turnit/__init__.py
turnit/turnit.py
turnit-0.1.data/scripts/turnit
turnit-0.1.dist-info/METADATA
turnit-0.1.dist-info/WHEEL
turnit-0.1.dist-info/top_level.txt
turnit-0.1.dist-info/RECORD
